fucker_zju/__init__.py
fucker_zju/cal_ifp.py
fucker_zju/task.py
fucker_zju/util_post_process.py
fucker_zju/wp.py
fucker_zju/Models/CarsiDock/RTMScore/__pycache__/utils.cpython-38.pyc
fucker_zju/Models/CarsiDock/RTMScore/data/__pycache__/__init__.cpython-38.pyc
fucker_zju/Models/CarsiDock/RTMScore/data/__pycache__/data.cpython-38.pyc
fucker_zju/Models/CarsiDock/RTMScore/feats/__pycache__/__init__.cpython-38.pyc
fucker_zju/Models/CarsiDock/RTMScore/feats/__pycache__/extract_pocket_prody.cpython-38.pyc
fucker_zju/Models/CarsiDock/RTMScore/feats/__pycache__/mol2graph_rdmda_res.cpython-38.pyc
fucker_zju/Models/CarsiDock/RTMScore/model/__pycache__/__init__.cpython-38.pyc
fucker_zju/Models/CarsiDock/RTMScore/model/__pycache__/model2.cpython-38.pyc
fucker_zju/Models/CarsiDock/RTMScore/model/__pycache__/utils.cpython-38.pyc
fucker_zju/Models/CarsiDock/src/__pycache__/__init__.cpython-38.pyc
fucker_zju/Models/CarsiDock/src/data/__pycache__/__init__.cpython-38.pyc
fucker_zju/Models/CarsiDock/src/data/__pycache__/dictionary.cpython-38.pyc
fucker_zju/Models/CarsiDock/src/layers/__pycache__/__init__.cpython-38.pyc
fucker_zju/Models/CarsiDock/src/layers/__pycache__/modeling_layers.cpython-38.pyc
fucker_zju/Models/CarsiDock/src/layers/__pycache__/modeling_outputs.cpython-38.pyc
fucker_zju/Models/CarsiDock/src/layers/openfold/__pycache__/chunk_utils.cpython-38.pyc
fucker_zju/Models/CarsiDock/src/layers/openfold/__pycache__/model_utils.cpython-38.pyc
fucker_zju/Models/CarsiDock/src/layers/openfold/__pycache__/modeling_evoformer.cpython-38.pyc
fucker_zju/Models/CarsiDock/src/layers/openfold/__pycache__/tensor_utils.cpython-38.pyc
fucker_zju/Models/CarsiDock/src/modeling/__pycache__/__init__.cpython-38.pyc
fucker_zju/Models/CarsiDock/src/modeling/__pycache__/modeling_base_model.cpython-38.pyc
fucker_zju/Models/CarsiDock/src/modeling/__pycache__/modeling_foldock2.cpython-38.pyc
fucker_zju/Models/CarsiDock/src/utils/__pycache__/__init__.cpython-38.pyc
fucker_zju-1.8.6.dist-info/LICENSE
fucker_zju-1.8.6.dist-info/METADATA
fucker_zju-1.8.6.dist-info/WHEEL
fucker_zju-1.8.6.dist-info/entry_points.txt
fucker_zju-1.8.6.dist-info/top_level.txt
fucker_zju-1.8.6.dist-info/RECORD
