Metadata-Version: 2.1
Name: fucker-zju
Version: 1.8.6
Summary: 一个非常NB的包
Author: 凯子哥
Author-email: 1156537327@qq.com
Classifier: Programming Language :: Python :: 3
Classifier: License :: OSI Approved :: MIT License
Classifier: Operating System :: OS Independent
Requires-Python: >=3
License-File: LICENSE
Requires-Dist: pillow
